<entry identifier="747f83bb-6c05-4cd5-988a-fb569c167287" index="1">
  <spell>中</spell>
  <usage category="noun" index="1">
    <semantics>
      一隅不偏。
    </semantics>
    <sample>中國</sample>
    <sample>中正</sample>
  </usage>
  <usage category="noun" index="2">
    <semantics>
      仲於上、中、下者。
    </semantics>
    <sample>中品</sample>
  </usage>
  <usage category="noun" index="3">
    <semantics>
      懷中。
    </semantics>
    <sample>此中有眞意</sample>
  </usage>
  <usage category="verb" index="4">
    <semantics>
      至于正鵠。
    </semantics>
    <sample>百發百中</sample>
  </usage>
</entry>
